portwire/circuitlong/circuitlong.v
// Student Name: Matthew Wempe
// Program Name: Lab01 - circuitlong
// Creation Date: 01/23/18
// Last Modified Date: 01/24/18
// CSCI Course: CSCI-330
// Grade Received: A
// Comments: Works great!


// module is created.
module circuitlong(a,b,c,out1);

// input/output wires are set 
input wire a;
input wire b;
input wire c;
output wire out1;

// additional wires are created
wire nota;
wire notb;
wire notc;

wire Y0;
wire Y1;
wire Y2;
wire Y3;
wire Y4;
// nots are created 
not(nota, a);
not(notb, b);
not(notc, c);

// ands are made useing previous wires
and(Y0, nota, notb, c);
and(Y1, a, notb, notc);
and(Y2, a, notb, c);
and(Y3, a, b, notc);
and(Y4, a, b, c);
// or is assigned and output is assigned 
or(out1,Y0,Y1,Y2,Y3,Y4);

//end module
endmodule

portwire/circuitlong/circuitlong-test.v
// test that ouputs every possible option if a wire has a current or does not have a current. 


module circuitlongtest();

reg atest, btest, ctest;
wire f;

circuitlong DUT(atest,btest,ctest,f);

initial
begin
	$dumpfile("circuitlong.vcd");
	$dumpvars(0, DUT);

	atest <= 0; btest <= 0; ctest <= 0;
	#5
	$display("atest = %d, btest = %d, ctest = %d, f = %d", atest, btest, ctest, f);

	atest <= 0; btest <= 0; ctest <= 1;
 	#5
 	$display("atest = %d, btest = %d, ctest = %d, f = %d", atest, btest, ctest, f);

 	atest <= 0; btest <= 1; ctest <= 0;
 	#5
 	$display("atest = %d, btest = %d, ctest = %d, f = %d", atest, btest, ctest, f);

 	atest <= 1; btest <= 0; ctest <= 0;
 	#5
 	$display("atest = %d, btest = %d, ctest = %d, f = %d", atest, btest, ctest, f);

 	atest <= 0; btest <= 1; ctest <= 1;
 	#5
 	$display("atest = %d, btest = %d, ctest = %d, f = %d", atest, btest, ctest, f);

 	atest <= 1; btest <= 1; ctest <= 1;
 	#5
 	$display("atest = %d, btest = %d, ctest = %d, f = %d", atest, btest, ctest, f);

 	atest <= 1; btest <= 0; ctest <= 1;
 	#5
 	$display("atest = %d, btest = %d, ctest = %d, f = %d", atest, btest, ctest, f);

 	atest <= 1; btest <= 1; ctest <= 0;
 	#5
 	$display("atest = %d, btest = %d, ctest = %d, f = %d", atest, btest, ctest, f);

end

endmodule

portwire/circuitlong/circuitlong.vcd
$date
	Fri Apr  6 13:20:38 2018
$end
$version
	Icarus Verilog
$end
$timescale
	1s
$end
$scope module circuitlongtest $end
$scope module DUT $end
$var wire 1 ! Y0 $end
$var wire 1 " Y1 $end
$var wire 1 # Y2 $end
$var wire 1 $ Y3 $end
$var wire 1 % Y4 $end
$var wire 1 & a $end
$var wire 1 ' b $end
$var wire 1 ( c $end
$var wire 1 ) nota $end
$var wire 1 * notb $end
$var wire 1 + notc $end
$var wire 1 , out1 $end
$upscope $end
$upscope $end
$enddefinitions $end
#0
$dumpvars
0,
1+
1*
1)
0(
0'
0&
0%
0$
0#
0"
0!
$end
#5
1,
0+
1!
1(
#10
0,
1+
0!
0*
0(
1'
#15
1,
1"
1*
0)
0'
1&
#20
0,
0+
0*
1)
0"
1(
1'
0&
#25
1,
0)
1%
1&
#30
1,
1#
1*
0%
0'
#35
1,
1$
1+
0#
0*
0(
1'
