portwire/circuitshort/circuitshort.v
// Student Name: Matthew Wempe
// Program Name: Lab01 - circuitshort
// Creation Date: 01/23/18
// Last Modified Date: 01/24/18
// CSCI Course: CSCI-330
// Grade Received: A
// Comments: Works great!

//module is created
module circuitshort(a,b,c, out1);
// wires are assigned
input wire a;
input wire b;
input wire c;
output wire out1;

wire notb;

wire Y0;
// not has wires assigned
not(notb, b);
// and has wires assigned
and(Y0, notb, c);
// or is assigned and ouput goes to ou1
or(out1, Y0, a);
// module end
endmodule

portwire/circuitshort/circuitshort-test.v
// test that ouputs every possible option if a wire has a current or does not have a current.

module circuitshorttest();

reg atest,btest,ctest;
wire f;

circuitshort DUT(atest,btest,ctest,f);

initial
begin
        $dumpfile("circuitshort.vcd");
        $dumpvars(0, DUT);

        atest <= 0; btest <= 0; ctest <= 0;
        #5
        $display("atest = %d, btest = %d, ctest = %d, f = %d", atest, btest, ctest, f);

        atest <= 0; btest <= 0; ctest <= 1;
        #5
        $display("atest = %d, btest = %d, ctest = %d, f = %d", atest, btest, ctest, f);

        atest <= 0; btest <= 1; ctest <= 0;
        #5
        $display("atest = %d, btest = %d, ctest = %d, f = %d", atest, btest, ctest, f);

        atest <= 1; btest <= 0; ctest <= 0;
        #5
        $display("atest = %d, btest = %d, ctest = %d, f = %d", atest, btest, ctest, f);

        atest <= 0; btest <= 1; ctest <= 1;
        #5
        $display("atest = %d, btest = %d, ctest = %d, f = %d", atest, btest, ctest, f);

        atest <= 1; btest <= 1; ctest <= 1;
        #5
        $display("atest = %d, btest = %d, ctest = %d, f = %d", atest, btest, ctest, f);

        atest <= 1; btest <= 0; ctest <= 1;
        #5
        $display("atest = %d, btest = %d, ctest = %d, f = %d", atest, btest, ctest, f);

        atest <= 1; btest <= 1; ctest <= 0;
        #5
        $display("atest = %d, btest = %d, ctest = %d, f = %d", atest, btest, ctest, f);

end

endmodule

portwire/circuitshort/circuitshort.vcd
$date
	Fri Apr  6 13:25:41 2018
$end
$version
	Icarus Verilog
$end
$timescale
	1s
$end
$scope module circuitshorttest $end
$scope module DUT $end
$var wire 1 ! Y0 $end
$var wire 1 " a $end
$var wire 1 # b $end
$var wire 1 $ c $end
$var wire 1 % notb $end
$var wire 1 & out1 $end
$upscope $end
$upscope $end
$enddefinitions $end
#0
$dumpvars
0&
1%
0$
0#
0"
0!
$end
#5
1&
1!
1$
#10
0&
0!
0%
0$
1#
#15
1%
1&
0#
1"
#20
0%
0&
1$
1#
0"
#25
1&
1"
#30
1!
1%
0#
#35
0!
0%
0$
1#
